LICENSE.txt
README.md
setup.py
bin/gltf-op
gltf/__init__.py
gltf/animations.py
gltf/buffers.py
gltf/gltf.py
gltf/materials.py
gltf/nodes.py
gltf/ops.py
gltf/utils.py
gltf.egg-info/PKG-INFO
gltf.egg-info/SOURCES.txt
gltf.egg-info/dependency_links.txt
gltf.egg-info/not-zip-safe
gltf.egg-info/requires.txt
gltf.egg-info/top_level.txt