Metadata-Version: 2.1
Name: gltf
Version: 0.7.21
Summary: Load, modify, and save GLTF files.
Home-page: https://gitlab.com/seekxr/py-gltf
Author: Trey Nelson
Author-email: trey@seekxr.com
License: MIT
Classifier: Programming Language :: Python :: 2.7
Classifier: Programming Language :: Python :: 3.6
Classifier: Programming Language :: Python :: 3.7
Classifier: Topic :: Multimedia :: Graphics :: 3D Modeling
License-File: LICENSE.txt
